{
	"movies": [
		{
			"Rank": "1",
			"Title": "Portrait of a Lady on Fire",
			"Director": "Celine Sciamma",
			"Country": "France",
			"Year": "2019"
		},
		{
			"Rank": "2",
			"Title": "Come and See",
			"Director": "Elem Klimov",
			"Country": "USSR",
			"Year": "1985"
		},
		{
			"Rank": "3",
			"Title": "In the Mood for Love",
			"Director": "Wong Kar-wai",
			"Country": "China",
			"Year": "2000"
		},
		{
			"Rank": "4",
			"Title": "Paris, Texas",
			"Director": "Wim Wenders",
			"Country": "USA",
			"Year": "1984"
		},
		{
			"Rank": "5",
			"Title": "High and Low",
			"Director": "Akira Kurosawa",
			"Country": "Japan",
			"Year": "1963"
		}
	]
}